RecruitmentCurveFitting/CurveFitting.py
RecruitmentCurveFitting/RecruitmentCurves.py
RecruitmentCurveFitting/__init__.py
RecruitmentCurveFitting/__main__.py
RecruitmentCurveFitting/example-data1.txt
RecruitmentCurveFitting/example-data2.txt
RecruitmentCurveFitting/example-waveforms.csv
recruitmentcurvefitting-1.2.7.dist-info/METADATA
recruitmentcurvefitting-1.2.7.dist-info/WHEEL
recruitmentcurvefitting-1.2.7.dist-info/top_level.txt
recruitmentcurvefitting-1.2.7.dist-info/RECORD
