Metadata-Version: 2.1
Name: RecruitmentCurveFitting
Version: 1.2.7
Summary: A package for fitting sigmoid and bell-shaped functions to EMG recruitment-curve measurements
Author: Jeremy Hill
Author-email: jezhill@gmail.com
License: CC0
Requires-Python: >=2.7, !=3.0.*, !=3.1.*, !=3.2.*, <4
Requires-Dist: numpy
Requires-Dist: scipy
Requires-Dist: matplotlib
